Workbook

Sheet Methodology
A1: Combined 7-EA Portfolio Ledger - Methodology & Limitations (Full history: 2023-01-03 .. 2026-08-14)
A3: What this workbook is
A4: A single combined trade-for-trade ledger and per-EA attribution summary for all SEVEN systems - Aurelius_EA.mq5 (M5), Aurelius_M15_EA.mq5, Vanguard_EA.mq5 (M5), Vanguard_M15_EA.mq5, Meridian_EA.mq5, Ratchet_EA.mq5 and MSG_Trader_EA.mq5 - trading together against ONE shared account, starting balance 13,500 USD.
A5: Window covered: 2023-01-03 01:00 to 2026-08-14 23:55 (broker server time).
A7: LIMITATION 1 - this is a Python-model combination, not a real 7-EA MT5 run
A8: No real simultaneous 7-EA MT5 run exists or could easily exist - these are normally seven independent live accounts/charts. Each system's trades come from its OWN already-validated Python simulator at its OWN current shipped-default parameters (research/overlap/trades.py for the first six; research/msg/sim.py's simulate() with Params() for MSG). All seven use the project's established pnl convention (USD, no compounding), but NOT all at the same position size: the six overlap-study systems' pnl is on a 0.01-lot / 1oz basis (Ratchet sim.py: "All P/L is USD per 0.01 lot (1 oz)"; Meridian msim.py: "P/L is USD per 0.01 lot (1 oz)"; Aurelius/Vanguard's pnl is the raw price difference, the same convention with no multiplier). MSG_Trader_EA.mq5's OWN shipped default lot size is 0.03 (Params.lots), i.e. THREE TIMES that basis - used AS-IS here because the point of this workbook is each EA's own real shipped configuration, not one artificial common lot size. Applying any of this against a real 13,500-USD account is a useful approximation, NOT the same as a real live account: real spread/swap/slippage/margin/execution differences exist, exactly as this project's own real-vs-Python comparisons have repeatedly found this session.
A10: LIMITATION 2 - ledger ordering: by EXIT time, not entry time
A11: All seven systems' trades are merged into ONE chronological ledger ordered by EXIT time - the moment a trade's pnl actually realizes into balance, matching how MT5's own Balance column updates on deal close (not on open). Running balance starts at 13,500 and updates by each trade's pnl in that exit-time order.
A13: LIMITATION 3 - no shared margin/exposure simulation
A14: This is a straightforward realized-pnl ledger - seven independent pnl streams stacked onto one running balance - NOT a margin simulation. It does not model shared margin or exposure limits across the seven systems trading "at once" on one real account.
A16: Data coverage
A17: Aurelius/Vanguard (M5 and M15): GOLD# M5 export, 2023-01-03 01:00 .. 2026-08-14 23:55. Meridian/Ratchet: a different GOLD# M5 export, 2022-06-27 04:30 .. 2026-09-18 23:55 (same broker/symbol feed, confirmed by both CSVs' own meta_symbol=GOLD# header - see research/overlap/trades.py's own docstring for the full reasoning). This workbook's window (Full history: 2023-01-03 .. 2026-08-14) is bounded by these sources where relevant.
... A27: Generated 2026-09-24 09:58 local.

Sheet Trade Ledger
A1: Combined 7-EA Portfolio - Trade Ledger (Full history: 2023-01-03 .. 2026-08-14)
A2: Starting Balance (USD): | C2: 13500 | E2: Window: | F2: 2023-01-03 01:00 .. 2026-08-14 23:55
A4: # | B4: System | C4: Core Indicator / Signal | D4: Direction | E4: Entry Time | F4: Exit Time | G4: PnL (USD, this trade) | H4: Balance After (USD)
A5: 1 | B5: Ratchet | C5: Stochastic scalp with give-back trail exit | D5: Long | E5: 44929.069 | F5: 44929.128 | G5: 1.06 | H5: =$C$2+G5
A6: 2 | B6: Ratchet | C6: Stochastic scalp with give-back trail exit | D6: Long | E6: 44929.174 | F6: 44929.448 | G6: 5.64 | H6: =H5+G6
A7: 3 | B7: Meridian | C7: 21/50 MA cross, 250-period confirm filter, VWAP | D7: Long | E7: 44929.653 | F7: 44929.726 | G7: -4.16 | H7: =H6+G7
A8: 4 | B8: Meridian | C8: 21/50 MA cross, 250-period confirm filter, VWAP | D8: Short | E8: 44929.74 | F8: 44929.792 | G8: -7 | H8: =H7+G8
A9: 5 | B9: Ratchet | C9: Stochastic scalp with give-back trail exit | D9: Long | E9: 44929.865 | F9: 44929.997 | G9: 0.33 | H9: =H8+G9
A10: 6 | B10: Meridian | C10: 21/50 MA cross, 250-period confirm filter, VWAP | D10: Long | E10: 44929.833 | F10: 44930.076 | G10: -2.77 | H10: =H9+G10
A11: 7 | B11: Ratchet | C11: Stochastic scalp with give-back trail exit | D11: Long | E11: 44930.142 | F11: 44930.42 | G11: 19.34 | H11: =H10+G11
A12: 8 | B12: Ratchet | C12: Stochastic scalp with give-back trail exit | D12: Long | E12: 44930.476 | F12: 44930.483 | G12: 0.3 | H12: =H11+G12
A13: 9 | B13: Ratchet | C13: Stochastic scalp with give-back trail exit | D13: Long | E13: 44930.556 | F13: 44930.562 | G13: -2.4 | H13: =H12+G13
A14: 10 | B14: Meridian | C14: 21/50 MA cross, 250-period confirm filter, VWAP | D14: Long | E14: 44930.122 | F14: 44930.615 | G14: 14.58 | H14: =H13+G14
A15: 11 | B15: Meridian | C15: 21/50 MA cross, 250-period confirm filter, VWAP | D15: Long | E15: 44930.656 | F15: 44930.667 | G15: -4.46 | H15: =H14+G15
A16: 12 | B16: Ratchet | C16: Stochastic scalp with give-back trail exit | D16: Long | E16: 44930.674 | F16: 44930.701 | G16: -3.91 | H16: =H15+G16
A17: 13 | B17: Ratchet | C17: Stochastic scalp with give-back trail exit | D17: Long | E17: 44930.778 | F17: 44930.781 | G17: 0.26 | H17: =H16+G17
... A7406: 7402 | B7406: Vanguard_M5 | C7406: Trendline breakout (fractal swing line) + VWAP/S-R distance gate | D7406: Short | E7406: 46247.292 | F7406: 46248.997 | G7406: 24.14 | H7406: =H7405+G7406

Sheet Summary
A1: Combined 7-EA Portfolio - Summary / Attribution (Full history: 2023-01-03 .. 2026-08-14)
A4: System | B4: Core Indicator / Signal Family | C4: Trades | D4: Wins | E4: Win Rate % | F4: Gross Profit (USD) | G4: Gross Loss (USD) | H4: Profit Factor | I4: Net Contribution (USD) | J4: % of Portfolio Net Profit
A5: Aurelius_M5 | B5: MA alignment (EMA21>EMA50>SMA250>SMMA500 vs EMA2400 trend filter) | C5: =COUNTIF('Trade Ledger'!$B$5:$B$7406,A5) | D5: =COUNTIFS('Trade Ledger'!$B$5:$B$7406,A5,'Trade Ledger'!$G$5:$G$7406,">0") | E5: =IFERROR(D5/C5,0) | F5: =SUMIFS('Trade Ledger'!$G$5:$G$7406,'Trade Ledger'!$B$5:$B$7406,A5,'Trade Ledger'!$G$5:$G$7406,">0") | G5: =-SUMIFS('Trade Ledger'!$G$5:$G$7406,'Trade Ledger'!$B$5:$B$7406,A5,'Trade Ledger'!$G$5:$G$7406,"<0") | H5: =IFERROR(F5/G5,"") | I5: =SUMIF('Trade Ledger'!$B$5:$B$7406,A5,'Trade Ledger'!$G$5:$G$7406) | J5: =IFERROR(I5/$I$12,0)
A6: Aurelius_M15 | B6: MA alignment (EMA21>EMA50>SMA250>SMMA500 vs EMA2400 trend filter) - M15 chart | C6: =COUNTIF('Trade Ledger'!$B$5:$B$7406,A6) | D6: =COUNTIFS('Trade Ledger'!$B$5:$B$7406,A6,'Trade Ledger'!$G$5:$G$7406,">0") | E6: =IFERROR(D6/C6,0) | F6: =SUMIFS('Trade Ledger'!$G$5:$G$7406,'Trade Ledger'!$B$5:$B$7406,A6,'Trade Ledger'!$G$5:$G$7406,">0") | G6: =-SUMIFS('Trade Ledger'!$G$5:$G$7406,'Trade Ledger'!$B$5:$B$7406,A6,'Trade Ledger'!$G$5:$G$7406,"<0") | H6: =IFERROR(F6/G6,"") | I6: =SUMIF('Trade Ledger'!$B$5:$B$7406,A6,'Trade Ledger'!$G$5:$G$7406) | J6: =IFERROR(I6/$I$12,0)
A7: Vanguard_M5 | B7: Trendline breakout (fractal swing line) + VWAP/S-R distance gate | C7: =COUNTIF('Trade Ledger'!$B$5:$B$7406,A7) | D7: =COUNTIFS('Trade Ledger'!$B$5:$B$7406,A7,'Trade Ledger'!$G$5:$G$7406,">0") | E7: =IFERROR(D7/C7,0) | F7: =SUMIFS('Trade Ledger'!$G$5:$G$7406,'Trade Ledger'!$B$5:$B$7406,A7,'Trade Ledger'!$G$5:$G$7406,">0") | G7: =-SUMIFS('Trade Ledger'!$G$5:$G$7406,'Trade Ledger'!$B$5:$B$7406,A7,'Trade Ledger'!$G$5:$G$7406,"<0") | H7: =IFERROR(F7/G7,"") | I7: =SUMIF('Trade Ledger'!$B$5:$B$7406,A7,'Trade Ledger'!$G$5:$G$7406) | J7: =IFERROR(I7/$I$12,0)
A8: Vanguard_M15 | B8: Trendline breakout (fractal swing line) + VWAP/S-R distance gate - M15 chart | C8: =COUNTIF('Trade Ledger'!$B$5:$B$7406,A8) | D8: =COUNTIFS('Trade Ledger'!$B$5:$B$7406,A8,'Trade Ledger'!$G$5:$G$7406,">0") | E8: =IFERROR(D8/C8,0) | F8: =SUMIFS('Trade Ledger'!$G$5:$G$7406,'Trade Ledger'!$B$5:$B$7406,A8,'Trade Ledger'!$G$5:$G$7406,">0") | G8: =-SUMIFS('Trade Ledger'!$G$5:$G$7406,'Trade Ledger'!$B$5:$B$7406,A8,'Trade Ledger'!$G$5:$G$7406,"<0") | H8: =IFERROR(F8/G8,"") | I8: =SUMIF('Trade Ledger'!$B$5:$B$7406,A8,'Trade Ledger'!$G$5:$G$7406) | J8: =IFERROR(I8/$I$12,0)
A9: Meridian | B9: 21/50 MA cross, 250-period confirm filter, VWAP | C9: =COUNTIF('Trade Ledger'!$B$5:$B$7406,A9) | D9: =COUNTIFS('Trade Ledger'!$B$5:$B$7406,A9,'Trade Ledger'!$G$5:$G$7406,">0") | E9: =IFERROR(D9/C9,0) | F9: =SUMIFS('Trade Ledger'!$G$5:$G$7406,'Trade Ledger'!$B$5:$B$7406,A9,'Trade Ledger'!$G$5:$G$7406,">0") | G9: =-SUMIFS('Trade Ledger'!$G$5:$G$7406,'Trade Ledger'!$B$5:$B$7406,A9,'Trade Ledger'!$G$5:$G$7406,"<0") | H9: =IFERROR(F9/G9,"") | I9: =SUMIF('Trade Ledger'!$B$5:$B$7406,A9,'Trade Ledger'!$G$5:$G$7406) | J9: =IFERROR(I9/$I$12,0)
A10: Ratchet | B10: Stochastic scalp with give-back trail exit | C10: =COUNTIF('Trade Ledger'!$B$5:$B$7406,A10) | D10: =COUNTIFS('Trade Ledger'!$B$5:$B$7406,A10,'Trade Ledger'!$G$5:$G$7406,">0") | E10: =IFERROR(D10/C10,0) | F10: =SUMIFS('Trade Ledger'!$G$5:$G$7406,'Trade Ledger'!$B$5:$B$7406,A10,'Trade Ledger'!$G$5:$G$7406,">0") | G10: =-SUMIFS('Trade Ledger'!$G$5:$G$7406,'Trade Ledger'!$B$5:$B$7406,A10,'Trade Ledger'!$G$5:$G$7406,"<0") | H10: =IFERROR(F10/G10,"") | I10: =SUMIF('Trade Ledger'!$B$5:$B$7406,A10,'Trade Ledger'!$G$5:$G$7406) | J10: =IFERROR(I10/$I$12,0)
A11: MSG | B11: Session-range breakout + Fibonacci retracement-zone entry | C11: =COUNTIF('Trade Ledger'!$B$5:$B$7406,A11) | D11: =COUNTIFS('Trade Ledger'!$B$5:$B$7406,A11,'Trade Ledger'!$G$5:$G$7406,">0") | E11: =IFERROR(D11/C11,0) | F11: =SUMIFS('Trade Ledger'!$G$5:$G$7406,'Trade Ledger'!$B$5:$B$7406,A11,'Trade Ledger'!$G$5:$G$7406,">0") | G11: =-SUMIFS('Trade Ledger'!$G$5:$G$7406,'Trade Ledger'!$B$5:$B$7406,A11,'Trade Ledger'!$G$5:$G$7406,"<0") | H11: =IFERROR(F11/G11,"") | I11: =SUMIF('Trade Ledger'!$B$5:$B$7406,A11,'Trade Ledger'!$G$5:$G$7406) | J11: =IFERROR(I11/$I$12,0)
A12: PORTFOLIO TOTAL | B12: All 7 systems combined | C12: =SUM(C5:C11) | D12: =SUM(D5:D11) | E12: =IFERROR(D12/C12,0) | F12: =SUM(F5:F11) | G12: =SUM(G5:G11) | H12: =IFERROR(F12/G12,"") | I12: =SUM(I5:I11) | J12: 1
A14: Starting Balance (USD): | C14: ='Trade Ledger'!$C$2
A15: Final Balance (USD): | C15: ='Trade Ledger'!$C$2+I12
A16: Total Net Profit (USD): | C16: =I12
